cranial/common/config.py
cranial/common/logger.py
cranial/common/serialize.py
cranial/common/utils.py
cranial/connectors/__init__.py
cranial/connectors/base.py
cranial/connectors/googlecloudstorage.py
cranial/connectors/http.py
cranial/connectors/local.py
cranial/connectors/s3.py
cranial/coordinator.py
cranial/datastore/__init__.py
cranial/datastore/adapters/__init__.py
cranial/datastore/adapters/cassandra.py
cranial/datastore/adapters/psql.py
cranial/datastore/dbapi.py
cranial/fetcher.py
cranial/fetchers.py
cranial/keyvalue/README.rst
cranial/keyvalue/__init__.py
cranial/keyvalue/interceptor.py
cranial/keyvalue/keyvalue.py
cranial/keyvalue/kvandra.py
cranial/listeners/__init__.py
cranial/listeners/base.py
cranial/listeners/db.py
cranial/listeners/file.py
cranial/listeners/kafka.py
cranial/listeners/postgresql.py
cranial/listeners/stdin.py
cranial/listeners/zmq.py
cranial/messaging/README.rst
cranial/messaging/__init__.py
cranial/messaging/adapters/__init__.py
cranial/messaging/adapters/firehose.py
cranial/messaging/adapters/firehose_async.py
cranial/messaging/adapters/kafka.py
cranial/messaging/adapters/zmq.py
cranial/messaging/base.py
cranial/messaging/celery.py
cranial/messaging/file.py
cranial/messaging/firehose.py
cranial/messaging/httpget.py
cranial/messaging/httppost.py
cranial/messaging/httpspost.py
cranial/messaging/kafka.py
cranial/messaging/stdout.py
cranial/messaging/test/test_coordinator.py
cranial/messaging/zmq.py
cranial/pipe.py
cranial/scripts.py
cranial/servicediscovery/base.py
cranial/servicediscovery/echo.py
cranial/servicediscovery/marathon.py
cranial_messaging-0.5.2.dist-info/entry_points.txt
cranial_messaging-0.5.2.dist-info/LICENSE
cranial_messaging-0.5.2.dist-info/WHEEL
cranial_messaging-0.5.2.dist-info/METADATA
cranial_messaging-0.5.2.dist-info/RECORD
